{
  "pacenote_616995757.ogg": {
    "audioLen": "0.848844"
  },
  "pacenote_348707044.ogg": {
    "audioLen": "0.567846"
  },
  "pacenote_68669174.ogg": {
    "audioLen": "0.371701"
  },
  "pacenote_1348630117.ogg": {
    "audioLen": "0.706712"
  },
  "pacenote_1933442513.ogg": {
    "audioLen": "0.917687"
  },
  "pacenote_1974850219.ogg": {
    "audioLen": "0.80898"
  },
  "pacenote_1828155399.ogg": {
    "audioLen": "1.073379"
  },
  "pacenote_2102319466.ogg": {
    "audioLen": "0.466304"
  },
  "pacenote_402072430.ogg": {
    "audioLen": "0.495601"
  },
  "pacenote_88843939.ogg": {
    "audioLen": "0.542404"
  },
  "pacenote_942803303.ogg": {
    "audioLen": "0.529206"
  },
  "pacenote_265314279.ogg": {
    "audioLen": "2.060227"
  },
  "pacenote_1721811807.ogg": {
    "audioLen": "2.422494"
  },
  "pacenote_745703893.ogg": {
    "audioLen": "2.285578"
  },
  "pacenote_2011201003.ogg": {
    "audioLen": "1.456508"
  },
  "pacenote_1828570586.ogg": {
    "audioLen": "1.220907"
  },
  "pacenote_1581529497.ogg": {
    "audioLen": "2.79161"
  },
  "pacenote_1257327315.ogg": {
    "audioLen": "3.18576"
  },
  "pacenote_103942043.ogg": {
    "audioLen": "3.175964"
  },
  "pacenote_1816660744.ogg": {
    "audioLen": "1.078639"
  },
  "pacenote_1479756031.ogg": {
    "audioLen": "0.946213"
  },
  "pacenote_63925256.ogg": {
    "audioLen": "1.053696"
  },
  "pacenote_1884944306.ogg": {
    "audioLen": "0.955782"
  },
  "pacenote_1645093974.ogg": {
    "audioLen": "1.513379"
  },
  "pacenote_1492899349.ogg": {
    "audioLen": "1.202676"
  },
  "pacenote_1992149857.ogg": {
    "audioLen": "2.12907"
  },
  "pacenote_1477246715.ogg": {
    "audioLen": "2.075556"
  },
  "pacenote_426302844.ogg": {
    "audioLen": "2.252426"
  },
  "pacenote_442448181.ogg": {
    "audioLen": "3.081587"
  },
  "pacenote_565120110.ogg": {
    "audioLen": "0.869569"
  },
  "pacenote_1828292674.ogg": {
    "audioLen": "0.936054"
  },
  "pacenote_1671846889.ogg": {
    "audioLen": "1.248254"
  },
  "pacenote_979494698.ogg": {
    "audioLen": "1.646984"
  },
  "pacenote_64729867.ogg": {
    "audioLen": "1.801497"
  },
  "pacenote_1721822087.ogg": {
    "audioLen": "1.148617"
  },
  "pacenote_1040042431.ogg": {
    "audioLen": "3.819229"
  },
  "pacenote_1457053361.ogg": {
    "audioLen": "3.723401"
  },
  "pacenote_1117259847.ogg": {
    "audioLen": "1.363311"
  },
  "pacenote_1558384622.ogg": {
    "audioLen": "2.78839"
  },
  "pacenote_948557835.ogg": {
    "audioLen": "0.998141"
  },
  "pacenote_580722774.ogg": {
    "audioLen": "1.124444"
  },
  "pacenote_1733799700.ogg": {
    "audioLen": "1.32576"
  },
  "pacenote_834138874.ogg": {
    "audioLen": "2.579955"
  },
  "pacenote_309397267.ogg": {
    "audioLen": "1.227664"
  },
  "pacenote_1447841504.ogg": {
    "audioLen": "3.984898"
  },
  "pacenote_1538768215.ogg": {
    "audioLen": "4.836961"
  },
  "pacenote_926275304.ogg": {
    "audioLen": "3.083311"
  },
  "pacenote_2044452434.ogg": {
    "audioLen": "2.841088"
  },
  "pacenote_1309915783.ogg": {
    "audioLen": "1.26576"
  },
  "pacenote_1091097744.ogg": {
    "audioLen": "1.080726"
  },
  "pacenote_46478773.ogg": {
    "audioLen": "2.714603"
  },
  "pacenote_1339633581.ogg": {
    "audioLen": "1.773061"
  },
  "pacenote_239565649.ogg": {
    "audioLen": "1.314739"
  },
  "pacenote_1748844873.ogg": {
    "audioLen": "3.211837"
  },
  "pacenote_1132144946.ogg": {
    "audioLen": "3.310884"
  },
  "pacenote_114238539.ogg": {
    "audioLen": "2.996054"
  },
  "pacenote_1299332645.ogg": {
    "audioLen": "0.899955"
  },
  "pacenote_1070613651.ogg": {
    "audioLen": "2.227392"
  },
  "pacenote_1963860281.ogg": {
    "audioLen": "4.433016"
  },
  "pacenote_2144686310.ogg": {
    "audioLen": "4.877143"
  },
  "pacenote_387583686.ogg": {
    "audioLen": "3.372245"
  },
  "pacenote_1602974558.ogg": {
    "audioLen": "0.84059"
  }
}